SciBot/Base.py
SciBot/LLMAnthropic.py
SciBot/LLMOpenAI.py
SciBot/LLMs.py
SciBot/__init__.py
SciBot/_version.py
SciBot/bots.py
SciBot/dbase.py
SciBot/image_embedding.py
SciBot/ingest.py
SciBot/tool_bots.py
SciBot/tool_classify.py
SciBot/tool_scores_pairwise.py
SciBot/visualize.py
SciToolsSciBot-1.0.8.dist-info/LICENSE
SciToolsSciBot-1.0.8.dist-info/METADATA
SciToolsSciBot-1.0.8.dist-info/WHEEL
SciToolsSciBot-1.0.8.dist-info/entry_points.txt
SciToolsSciBot-1.0.8.dist-info/top_level.txt
SciToolsSciBot-1.0.8.dist-info/RECORD
