Metadata-Version: 2.1
Name: SciToolsSciBot
Version: 1.0.8
Summary: SciBot scripts for domain-specific chatbot.
Home-page: https://github.com/CFN-softbio/SciBot
Author: Kevin Yager
Author-email: kyager@bnl.gov
License: BSD (3-clause)
Keywords: LLM
Platform: UNKNOWN
Classifier: Development Status :: 5 - Production/Stable
Classifier: Natural Language :: English
Classifier: Programming Language :: Python :: 3
Requires-Python: >=3.7
Requires-Dist: mysql-connector-python
Requires-Dist: numpy
Requires-Dist: openai
